qeschema/__init__.py
qeschema/cards.py
qeschema/converters.py
qeschema/documents.py
qeschema/exceptions.py
qeschema/namespaces.py
qeschema/options.py
qeschema/upf.py
qeschema/utils.py
qeschema/hdf5/__init__.py
qeschema/schemas/epw.xsd
qeschema/schemas/ph_xmlschema.xsd
qeschema/schemas/qes.xsd
qeschema/schemas/qes_neb.xsd
qeschema/schemas/qes_neb_test_ref.xsd
qeschema/schemas/qes_spectrum.xsd
qeschema/schemas/qes_test_ref.xsd
qeschema/schemas/tddfpt.xsd
qeschema/schemas/xspectra.xsd
qeschema/schemas/releases/ph-20180511.xsd
qeschema/schemas/releases/ph-20210706.xsd
qeschema/schemas/releases/ph_temp.xsd
qeschema/schemas/releases/qes-20180510.xsd
qeschema/schemas/releases/qes-20180511.xsd
qeschema/schemas/releases/qes_030920.xsd
qeschema/schemas/releases/qes_181201.xsd
qeschema/schemas/releases/qes_190207.xsd
qeschema/schemas/releases/qes_190304.xsd
qeschema/schemas/releases/qes_190719.xsd
qeschema/schemas/releases/qes_191206.xsd
qeschema/schemas/releases/qes_200420.xsd
qeschema/schemas/releases/qes_211101.xsd
qeschema/schemas/releases/qes_230310.xsd
qeschema/schemas/releases/qes_neb-20180511.xsd
qeschema/schemas/releases/qes_neb-211101.xsd
qeschema/schemas/releases/qes_spectrum-20180511.xsd
qeschema/schemas/releases/qes_spectrum-20180517.xsd
qeschema/schemas/releases/qes_test_240411.xsd
qeschema/schemas/releases/tddfpt-20180511.xsd
qeschema/schemas/releases/tddfpt-20180517.xsd
qeschema-1.5.2.data/scripts/xml2qeinput.py
qeschema-1.5.2.data/scripts/yaml2qeinput.py
qeschema-1.5.2.dist-info/LICENSE
qeschema-1.5.2.dist-info/METADATA
qeschema-1.5.2.dist-info/WHEEL
qeschema-1.5.2.dist-info/top_level.txt
qeschema-1.5.2.dist-info/RECORD
