Metadata-Version: 2.1
Name: qeschema
Version: 1.5.2
Summary: Schema-based tools and interfaces for Quantum Espresso data
Home-page: https://github.com/QEF/qeschema
License: MIT
Classifier: Development Status :: 5 - Production/Stable
Classifier: Intended Audience :: Science/Research
Classifier: License :: OSI Approved :: MIT License
Classifier: Operating System :: OS Independent
Classifier: Programming Language :: Python
Classifier: Programming Language :: Python :: 3
Classifier: Programming Language :: Python :: 3 :: Only
Classifier: Programming Language :: Python :: 3.7
Classifier: Programming Language :: Python :: 3.8
Classifier: Programming Language :: Python :: 3.9
Classifier: Programming Language :: Python :: 3.10
Classifier: Programming Language :: Python :: 3.11
Classifier: Programming Language :: Python :: 3.12
Classifier: Programming Language :: Python :: Implementation :: CPython
Classifier: Topic :: Scientific/Engineering :: Physics
Classifier: Topic :: Utilities
License-File: LICENSE
Requires-Dist: xmlschema <4.0.0,>=2.5.1
Requires-Dist: numpy
Provides-Extra: hdf5
Requires-Dist: h5py ; extra == 'hdf5'
Provides-Extra: yaml
Requires-Dist: pyyaml ; extra == 'yaml'
